{
    "os": "Linux-5.4.0-135-generic-x86_64-with-glibc2.31",
    "python": "3.10.9",
    "heartbeatAt": "2023-03-14T07:09:23.310050",
    "startedAt": "2023-03-14T07:09:22.841598",
    "docker": null,
    "cuda": null,
    "args": [
        "--cfg=configs/alexnet_base.yaml"
    ],
    "state": "running",
    "program": "/home/narisam/sp23-nmep-hw1/main.py",
    "codePath": "main.py",
    "git": {
        "remote": "git@github.com:natehaynam/mlab-cv-module.git",
        "commit": "75ca56f99062b5c070d29bcb1ff0e06094a45b77"
    },
    "email": null,
    "root": "/home/narisam/sp23-nmep-hw1",
    "host": "honeydew",
    "username": "narisam",
    "executable": "/home/narisam/miniconda3/bin/python",
    "cpu_count": 32,
    "cpu_count_logical": 64,
    "cpu_freq": {
        "current": 1966.6490468750003,
        "min": 1000.0,
        "max": 3900.0
    },
    "cpu_freq_per_core": [
        {
            "current": 2254.428,
            "min": 1000.0,
            "max": 3900.0
        },
        {
            "current": 2300.987,
            "min": 1000.0,
            "max": 3900.0
        },
        {
            "current": 1445.469,
            "min": 1000.0,
            "max": 3900.0
        },
        {
            "current": 2299.999,
            "min": 1000.0,
            "max": 3900.0
        },
        {
            "current": 2143.934,
            "min": 1000.0,
            "max": 3900.0
        },
        {
            "current": 1365.892,
            "min": 1000.0,
            "max": 3900.0
        },
        {
            "current": 1100.012,
            "min": 1000.0,
            "max": 3900.0
        },
        {
            "current": 1599.899,
            "min": 1000.0,
            "max": 3900.0
        },
        {
            "current": 2150.336,
            "min": 1000.0,
            "max": 3900.0
        },
        {
            "current": 2300.142,
            "min": 1000.0,
            "max": 3900.0
        },
        {
            "current": 2556.408,
            "min": 1000.0,
            "max": 3900.0
        },
        {
            "current": 2299.998,
            "min": 1000.0,
            "max": 3900.0
        },
        {
            "current": 2177.449,
            "min": 1000.0,
            "max": 3900.0
        },
        {
            "current": 2158.49,
            "min": 1000.0,
            "max": 3900.0
        },
        {
            "current": 2215.836,
            "min": 1000.0,
            "max": 3900.0
        },
        {
            "current": 1405.407,
            "min": 1000.0,
            "max": 3900.0
        },
        {
            "current": 2167.417,
            "min": 1000.0,
            "max": 3900.0
        },
        {
            "current": 1873.665,
            "min": 1000.0,
            "max": 3900.0
        },
        {
            "current": 2302.022,
            "min": 1000.0,
            "max": 3900.0
        },
        {
            "current": 2148.836,
            "min": 1000.0,
            "max": 3900.0
        },
        {
            "current": 1321.362,
            "min": 1000.0,
            "max": 3900.0
        },
        {
            "current": 2592.169,
            "min": 1000.0,
            "max": 3900.0
        },
        {
            "current": 1238.269,
            "min": 1000.0,
            "max": 3900.0
        },
        {
            "current": 1237.968,
            "min": 1000.0,
            "max": 3900.0
        },
        {
            "current": 1595.272,
            "min": 1000.0,
            "max": 3900.0
        },
        {
            "current": 1170.672,
            "min": 1000.0,
            "max": 3900.0
        },
        {
            "current": 1667.162,
            "min": 1000.0,
            "max": 3900.0
        },
        {
            "current": 1557.716,
            "min": 1000.0,
            "max": 3900.0
        },
        {
            "current": 2569.536,
            "min": 1000.0,
            "max": 3900.0
        },
        {
            "current": 1706.414,
            "min": 1000.0,
            "max": 3900.0
        },
        {
            "current": 2258.326,
            "min": 1000.0,
            "max": 3900.0
        },
        {
            "current": 2445.644,
            "min": 1000.0,
            "max": 3900.0
        },
        {
            "current": 2270.301,
            "min": 1000.0,
            "max": 3900.0
        },
        {
            "current": 2212.054,
            "min": 1000.0,
            "max": 3900.0
        },
        {
            "current": 1450.79,
            "min": 1000.0,
            "max": 3900.0
        },
        {
            "current": 2300.871,
            "min": 1000.0,
            "max": 3900.0
        },
        {
            "current": 2148.723,
            "min": 1000.0,
            "max": 3900.0
        },
        {
            "current": 1351.893,
            "min": 1000.0,
            "max": 3900.0
        },
        {
            "current": 1060.939,
            "min": 1000.0,
            "max": 3900.0
        },
        {
            "current": 1600.031,
            "min": 1000.0,
            "max": 3900.0
        },
        {
            "current": 2132.694,
            "min": 1000.0,
            "max": 3900.0
        },
        {
            "current": 2193.194,
            "min": 1000.0,
            "max": 3900.0
        },
        {
            "current": 2247.642,
            "min": 1000.0,
            "max": 3900.0
        },
        {
            "current": 2300.003,
            "min": 1000.0,
            "max": 3900.0
        },
        {
            "current": 2203.281,
            "min": 1000.0,
            "max": 3900.0
        },
        {
            "current": 2194.29,
            "min": 1000.0,
            "max": 3900.0
        },
        {
            "current": 2239.414,
            "min": 1000.0,
            "max": 3900.0
        },
        {
            "current": 1354.108,
            "min": 1000.0,
            "max": 3900.0
        },
        {
            "current": 2188.687,
            "min": 1000.0,
            "max": 3900.0
        },
        {
            "current": 1946.219,
            "min": 1000.0,
            "max": 3900.0
        },
        {
            "current": 2301.415,
            "min": 1000.0,
            "max": 3900.0
        },
        {
            "current": 1895.501,
            "min": 1000.0,
            "max": 3900.0
        },
        {
            "current": 1348.888,
            "min": 1000.0,
            "max": 3900.0
        },
        {
            "current": 2562.059,
            "min": 1000.0,
            "max": 3900.0
        },
        {
            "current": 1270.425,
            "min": 1000.0,
            "max": 3900.0
        },
        {
            "current": 1522.418,
            "min": 1000.0,
            "max": 3900.0
        },
        {
            "current": 1575.504,
            "min": 1000.0,
            "max": 3900.0
        },
        {
            "current": 1161.018,
            "min": 1000.0,
            "max": 3900.0
        },
        {
            "current": 1380.275,
            "min": 1000.0,
            "max": 3900.0
        },
        {
            "current": 1967.974,
            "min": 1000.0,
            "max": 3900.0
        },
        {
            "current": 2097.568,
            "min": 1000.0,
            "max": 3900.0
        },
        {
            "current": 1604.752,
            "min": 1000.0,
            "max": 3900.0
        },
        {
            "current": 2268.937,
            "min": 1000.0,
            "max": 3900.0
        },
        {
            "current": 2461.533,
            "min": 1000.0,
            "max": 3900.0
        }
    ],
    "disk": {
        "total": 3665.0068130493164,
        "used": 2644.767963409424
    },
    "gpu": "NVIDIA GeForce RTX 2080 Ti",
    "gpu_count": 8,
    "gpu_devices": [
        {
            "name": "NVIDIA GeForce RTX 2080 Ti",
            "memory_total": 11811160064
        },
        {
            "name": "NVIDIA GeForce RTX 2080 Ti",
            "memory_total": 11811160064
        },
        {
            "name": "NVIDIA GeForce RTX 2080 Ti",
            "memory_total": 11811160064
        },
        {
            "name": "NVIDIA GeForce RTX 2080 Ti",
            "memory_total": 11811160064
        },
        {
            "name": "NVIDIA GeForce RTX 2080 Ti",
            "memory_total": 11811160064
        },
        {
            "name": "NVIDIA GeForce RTX 2080 Ti",
            "memory_total": 11811160064
        },
        {
            "name": "NVIDIA GeForce RTX 2080 Ti",
            "memory_total": 11811160064
        },
        {
            "name": "NVIDIA GeForce RTX 2080 Ti",
            "memory_total": 11811160064
        }
    ],
    "memory": {
        "total": 503.54959869384766
    }
}
